{
	"configurations" : 
	[
		{
			"directories" : 
			[
				{
					"build" : ".",
					"jsonFile" : "directory-.-Debug-d0094a50bb2071803777.json",
					"minimumCMakeVersion" : 
					{
						"string" : "3.21"
					},
					"projectIndex" : 0,
					"source" : ".",
					"targetIndexes" : 
					[
						0
					]
				}
			],
			"name" : "Debug",
			"projects" : 
			[
				{
					"directoryIndexes" : 
					[
						0
					],
					"name" : "tp3_mina",
					"targetIndexes" : 
					[
						0
					]
				}
			],
			"targets" : 
			[
				{
					"directoryIndex" : 0,
					"id" : "tp3_mina::@6890427a1f51a3e7e1df",
					"jsonFile" : "target-tp3_mina-Debug-a4012772045f04caa362.json",
					"name" : "tp3_mina",
					"projectIndex" : 0
				}
			]
		}
	],
	"kind" : "codemodel",
	"paths" : 
	{
		"build" : "C:/Users/minab/CLionProjects/tp3_mina/cmake-build-debug",
		"source" : "C:/Users/minab/CLionProjects/tp3_mina"
	},
	"version" : 
	{
		"major" : 2,
		"minor" : 3
	}
}
